alu_control.v
`timescale 1ns/1ps

module alu_control (
    input  wire [6:0] opcode,
    input  wire [2:0] funct3,
    input  wire [6:0] funct7,

    output reg  [3:0] alu_control
);

    always @(*) begin

        // Default: ADD
        alu_control = 4'b0000;

        case (opcode)

            // --------------------------------
            // R-Type instructions
        
            7'b0110011: begin

                case (funct3)

                    // ADD / SUB
                    3'b000: begin
                        if (funct7 == 7'b0100000)
                            alu_control = 4'b0001; // SUB
                        else
                            alu_control = 4'b0000; // ADD
                    end

                    // AND
                    3'b111:
                        alu_control = 4'b0010;

                    // OR
                    3'b110:
                        alu_control = 4'b0011;

                    // XOR
                    3'b100:
                        alu_control = 4'b0100;

                    // SLT
                    3'b010:
                        alu_control = 4'b0101;

                    default:
                        alu_control = 4'b0000;

                endcase

            end

            // --------------------------------
            // I-Type ALU instructions
            // ADDI / ANDI / ORI
        
            7'b0010011: begin

                case (funct3)

                    // ADDI
                    3'b000:
                        alu_control = 4'b0000;

                    // ANDI
                    3'b111:
                        alu_control = 4'b0010;

                    // ORI
                    3'b110:
                        alu_control = 4'b0011;

                    default:
                        alu_control = 4'b0000;

                endcase

            end

            // --------------------------------
            // LW
            // Address = rs1 + immediate
       
            7'b0000011:
                alu_control = 4'b0000;

            // --------------------------------
            // SW
            // Address = rs1 + immediate
            7'b0100011:
                alu_control = 4'b0000;

            // --------------------------------
            // Branch
            // BEQ/BNE
            // Comparison uses subtraction
            
            7'b1100011:
                alu_control = 4'b0001;

            default:
                alu_control = 4'b0000;

        endcase

    end

endmodule

tb/alu_control_tb.v
`timescale 1ns/1ps

module alu_control_tb;

    reg  [6:0] opcode;
    reg  [2:0] funct3;
    reg  [6:0] funct7;

    wire [3:0] alu_control;

    alu_control uut (
        .opcode(opcode),
        .funct3(funct3),
        .funct7(funct7),
        .alu_control(alu_control)
    );

    initial begin

        $dumpfile("sim/alu_control.vcd");
        $dumpvars(0, alu_control_tb);

        $display("===== ALU CONTROL TEST =====");

        // ADD
        opcode = 7'b0110011;
        funct3 = 3'b000;
        funct7 = 7'b0000000;
        #10;
        $display("ADD : ALU Control = %b", alu_control);

        // SUB
        funct7 = 7'b0100000;
        #10;
        $display("SUB : ALU Control = %b", alu_control);

        // AND
        funct3 = 3'b111;
        funct7 = 7'b0000000;
        #10;
        $display("AND : ALU Control = %b", alu_control);

        // OR
        funct3 = 3'b110;
        #10;
        $display("OR  : ALU Control = %b", alu_control);

        // XOR
        funct3 = 3'b100;
        #10;
        $display("XOR : ALU Control = %b", alu_control);

        // SLT
        funct3 = 3'b010;
        #10;
        $display("SLT : ALU Control = %b", alu_control);

        // ADDI
        opcode = 7'b0010011;
        funct3 = 3'b000;
        #10;
        $display("ADDI: ALU Control = %b", alu_control);

        // LW
        opcode = 7'b0000011;
        #10;
        $display("LW  : ALU Control = %b", alu_control);

        // SW
        opcode = 7'b0100011;
        #10;
        $display("SW  : ALU Control = %b", alu_control);

        // BEQ/BNE
        opcode = 7'b1100011;
        #10;
        $display("BRANCH: ALU Control = %b", alu_control);

        $finish;

    end

endmodule

sim/alu_control.vcd
$date
	Sun Sep 13 23:02:51 2026
$end
$version
	Icarus Verilog
$end
$timescale
	1ps
$end
$scope module alu_control_tb $end
$var wire 4 ! alu_control [3:0] $end
$var reg 3 " funct3 [2:0] $end
$var reg 7 # funct7 [6:0] $end
$var reg 7 $ opcode [6:0] $end
$scope module uut $end
$var wire 3 % funct3 [2:0] $end
$var wire 7 & funct7 [6:0] $end
$var wire 7 ' opcode [6:0] $end
$var reg 4 ( alu_control [3:0] $end
$upscope $end
$upscope $end
$enddefinitions $end
$comment Show the parameter values. $end
$dumpall
$end
#0
$dumpvars
b0 (
b110011 '
b0 &
b0 %
b110011 $
b0 #
b0 "
b0 !
$end
#10000
b1 !
b1 (
b100000 #
b100000 &
#20000
b10 !
b10 (
b0 #
b0 &
b111 "
b111 %
#30000
b11 !
b11 (
b110 "
b110 %
#40000
b100 !
b100 (
b100 "
b100 %
#50000
b101 !
b101 (
b10 "
b10 %
#60000
b0 !
b0 (
b0 "
b0 %
b10011 $
b10011 '
#70000
b11 $
b11 '
#80000
b100011 $
b100011 '
#90000
b1 !
b1 (
b1100011 $
b1100011 '
