rtl/control_unit.v
`timescale 1ns/1ps

module control_unit (
    input  wire [6:0] opcode,

    output reg        reg_write,
    output reg        mem_read,
    output reg        mem_write,
    output reg        alu_src,
    output reg        mem_to_reg,
    output reg        branch,
    output reg        jump
);

    always @(*) begin

        // Default control signals
        reg_write = 1'b0;
        mem_read  = 1'b0;
        mem_write = 1'b0;
        alu_src   = 1'b0;
        mem_to_reg = 1'b0;
        branch    = 1'b0;
        jump      = 1'b0;

        case (opcode)

            // R-Type: ADD, SUB, AND, OR, XOR, SLT
            7'b0110011: begin
                reg_write = 1'b1;
                alu_src   = 1'b0;
                mem_to_reg = 1'b0;
            end

            // I-Type ALU: ADDI, ANDI, ORI
            7'b0010011: begin
                reg_write = 1'b1;
                alu_src   = 1'b1;
                mem_to_reg = 1'b0;
            end

            // LW
            7'b0000011: begin
                reg_write = 1'b1;
                mem_read  = 1'b1;
                alu_src   = 1'b1;
                mem_to_reg = 1'b1;
            end

            // SW
            7'b0100011: begin
                mem_write = 1'b1;
                alu_src   = 1'b1;
            end

            // Branch: BEQ, BNE
            7'b1100011: begin
                branch = 1'b1;
                alu_src = 1'b0;
            end

            // JAL
            7'b1101111: begin
                reg_write = 1'b1;
                jump      = 1'b1;
            end

            // LUI
            7'b0110111: begin
                reg_write = 1'b1;
                alu_src   = 1'b1;
            end

            // AUIPC
            7'b0010111: begin
                reg_write = 1'b1;
                alu_src   = 1'b1;
            end

            // Unsupported instruction
            default: begin
                reg_write = 1'b0;
                mem_read  = 1'b0;
                mem_write = 1'b0;
                alu_src   = 1'b0;
                mem_to_reg = 1'b0;
                branch    = 1'b0;
                jump      = 1'b0;
            end

        endcase

    end

endmodule

tb/control_unit_tb.v
`timescale 1ns/1ps

module control_unit_tb;

    reg  [6:0] opcode;

    wire reg_write;
    wire mem_read;
    wire mem_write;
    wire alu_src;
    wire mem_to_reg;
    wire branch;
    wire jump;

    control_unit uut (
        .opcode(opcode),
        .reg_write(reg_write),
        .mem_read(mem_read),
        .mem_write(mem_write),
        .alu_src(alu_src),
        .mem_to_reg(mem_to_reg),
        .branch(branch),
        .jump(jump)
    );

    task check_control;
        input expected_reg_write;
        input expected_mem_read;
        input expected_mem_write;
        input expected_alu_src;
        input expected_mem_to_reg;
        input expected_branch;
        input expected_jump;

        begin
            if ((reg_write  == expected_reg_write)  &&
                (mem_read   == expected_mem_read)   &&
                (mem_write  == expected_mem_write)  &&
                (alu_src    == expected_alu_src)    &&
                (mem_to_reg == expected_mem_to_reg) &&
                (branch     == expected_branch)    &&
                (jump       == expected_jump))
                $display("PASS");
            else
                $display("FAIL");
        end
    endtask

    initial begin

        $dumpfile("sim/control_unit.vcd");
        $dumpvars(0, control_unit_tb);

        $display("===== CONTROL UNIT DEEP VERIFICATION =====");

        // -----------------------------------------
        // R-Type
        // ADD, SUB, AND, OR, XOR, SLT
        // -----------------------------------------
        opcode = 7'b0110011;
        #10;

        $display("R-Type");
        $display("RegWrite=%b MemRead=%b MemWrite=%b ALUSrc=%b MemToReg=%b Branch=%b Jump=%b",
                 reg_write, mem_read, mem_write, alu_src,
                 mem_to_reg, branch, jump);

        check_control(1,0,0,0,0,0,0);


        // -----------------------------------------
        // I-Type ALU
        // ADDI, ANDI, ORI
        // -----------------------------------------
        opcode = 7'b0010011;
        #10;

        $display("I-Type ALU");
        $display("RegWrite=%b MemRead=%b MemWrite=%b ALUSrc=%b MemToReg=%b Branch=%b Jump=%b",
                 reg_write, mem_read, mem_write, alu_src,
                 mem_to_reg, branch, jump);

        check_control(1,0,0,1,0,0,0);


        // -----------------------------------------
        // LW
        // -----------------------------------------
        opcode = 7'b0000011;
        #10;

        $display("LW");
        $display("RegWrite=%b MemRead=%b MemWrite=%b ALUSrc=%b MemToReg=%b Branch=%b Jump=%b",
                 reg_write, mem_read, mem_write, alu_src,
                 mem_to_reg, branch, jump);

        check_control(1,1,0,1,1,0,0);


        // -----------------------------------------
        // SW
        // -----------------------------------------
        opcode = 7'b0100011;
        #10;

        $display("SW");
        $display("RegWrite=%b MemRead=%b MemWrite=%b ALUSrc=%b MemToReg=%b Branch=%b Jump=%b",
                 reg_write, mem_read, mem_write, alu_src,
                 mem_to_reg, branch, jump);

        check_control(0,0,1,1,0,0,0);


        // -----------------------------------------
        // BEQ
        // -----------------------------------------
        opcode = 7'b1100011;
        #10;

        $display("BEQ");
        $display("RegWrite=%b MemRead=%b MemWrite=%b ALUSrc=%b MemToReg=%b Branch=%b Jump=%b",
                 reg_write, mem_read, mem_write, alu_src,
                 mem_to_reg, branch, jump);

        check_control(0,0,0,0,0,1,0);


        // -----------------------------------------
        // BNE
        // Same opcode-level control as BEQ
        // -----------------------------------------
        opcode = 7'b1100011;
        #10;

        $display("BNE");
        $display("RegWrite=%b MemRead=%b MemWrite=%b ALUSrc=%b MemToReg=%b Branch=%b Jump=%b",
                 reg_write, mem_read, mem_write, alu_src,
                 mem_to_reg, branch, jump);

        check_control(0,0,0,0,0,1,0);


        // -----------------------------------------
        // JAL
        // -----------------------------------------
        opcode = 7'b1101111;
        #10;

        $display("JAL");
        $display("RegWrite=%b MemRead=%b MemWrite=%b ALUSrc=%b MemToReg=%b Branch=%b Jump=%b",
                 reg_write, mem_read, mem_write, alu_src,
                 mem_to_reg, branch, jump);

        check_control(1,0,0,0,0,0,1);


        // -----------------------------------------
        // LUI
        // -----------------------------------------
        opcode = 7'b0110111;
        #10;

        $display("LUI");
        $display("RegWrite=%b MemRead=%b MemWrite=%b ALUSrc=%b MemToReg=%b Branch=%b Jump=%b",
                 reg_write, mem_read, mem_write, alu_src,
                 mem_to_reg, branch, jump);

        check_control(1,0,0,1,0,0,0);


        // -----------------------------------------
        // AUIPC
        // -----------------------------------------
        opcode = 7'b0010111;
        #10;

        $display("AUIPC");
        $display("RegWrite=%b MemRead=%b MemWrite=%b ALUSrc=%b MemToReg=%b Branch=%b Jump=%b",
                 reg_write, mem_read, mem_write, alu_src,
                 mem_to_reg, branch, jump);

        check_control(1,0,0,1,0,0,0);


        // -----------------------------------------
        // Unsupported instruction
        // -----------------------------------------
        opcode = 7'b1111111;
        #10;

        $display("INVALID");
        $display("RegWrite=%b MemRead=%b MemWrite=%b ALUSrc=%b MemToReg=%b Branch=%b Jump=%b",
                 reg_write, mem_read, mem_write, alu_src,
                 mem_to_reg, branch, jump);

        check_control(0,0,0,0,0,0,0);


        $display("========================================");
        $display("CONTROL UNIT VERIFICATION COMPLETE");
        $display("========================================");

        $finish;

    end

endmodule

sim/control_unit.vcd
$date
	Mon Sep 14 23:10:08 2026
$end
$version
	Icarus Verilog
$end
$timescale
	1ps
$end
$scope module control_unit_tb $end
$var wire 1 ! reg_write $end
$var wire 1 " mem_write $end
$var wire 1 # mem_to_reg $end
$var wire 1 $ mem_read $end
$var wire 1 % jump $end
$var wire 1 & branch $end
$var wire 1 ' alu_src $end
$var reg 7 ( opcode [6:0] $end
$scope module uut $end
$var wire 7 ) opcode [6:0] $end
$var reg 1 ' alu_src $end
$var reg 1 & branch $end
$var reg 1 % jump $end
$var reg 1 $ mem_read $end
$var reg 1 # mem_to_reg $end
$var reg 1 " mem_write $end
$var reg 1 ! reg_write $end
$upscope $end
$scope task check_control $end
$var reg 1 * expected_alu_src $end
$var reg 1 + expected_branch $end
$var reg 1 , expected_jump $end
$var reg 1 - expected_mem_read $end
$var reg 1 . expected_mem_to_reg $end
$var reg 1 / expected_mem_write $end
$var reg 1 0 expected_reg_write $end
$upscope $end
$upscope $end
$enddefinitions $end
$comment Show the parameter values. $end
$dumpall
$end
#0
$dumpvars
x0
x/
x.
x-
x,
x+
x*
b110011 )
b110011 (
0'
0&
0%
0$
0#
0"
1!
$end
#10000
1'
1!
b10011 (
b10011 )
0,
0+
0.
0*
0/
0-
10
#20000
1#
1$
1'
1!
b11 (
b11 )
1*
#30000
1"
0#
1'
0$
0!
b100011 (
b100011 )
1.
1-
#40000
1&
0'
0"
b1100011 (
b1100011 )
0.
1/
0-
00
#50000
1+
0*
0/
#60000
1%
1!
0&
b1101111 (
b1101111 )
#70000
1'
0%
1!
b110111 (
b110111 )
1,
0+
10
#80000
1'
1!
b10111 (
b10111 )
0,
1*
#90000
0'
0!
b1111111 (
b1111111 )
#100000
0*
00
