rtl/program_counter.v
`timescale 1ns/1ps

module program_counter (
    input  wire        clk,
    input  wire        reset,

    input  wire [31:0] next_pc,

    output reg  [31:0] pc
);

    always @(posedge clk or posedge reset) begin

        if (reset)
            pc <= 32'b0;
        else
            pc <= next_pc;

    end

endmodule

tb/program_counter_tb.v
`timescale 1ns/1ps

module program_counter_tb;

    reg        clk;
    reg        reset;
    reg [31:0] next_pc;

    wire [31:0] pc;

    program_counter uut (
        .clk(clk),
        .reset(reset),
        .next_pc(next_pc),
        .pc(pc)
    );

    always #5 clk = ~clk;

    initial begin

        $dumpfile("sim/program_counter.vcd");
        $dumpvars(0, program_counter_tb);

        clk = 0;
        reset = 1;
        next_pc = 32'd0;

        #10;

        reset = 0;

        // PC = 4
        next_pc = 32'd4;
        #10;
        $display("PC = %d", pc);

        // PC = 8
        next_pc = 32'd8;
        #10;
        $display("PC = %d", pc);

        // PC = 12
        next_pc = 32'd12;
        #10;
        $display("PC = %d", pc);

        // PC = 16
        next_pc = 32'd16;
        #10;
        $display("PC = %d", pc);

        $finish;

    end

endmodule

sim/program_counter.vcd
$date
	Sun Sep 13 23:22:44 2026
$end
$version
	Icarus Verilog
$end
$timescale
	1ps
$end
$scope module program_counter_tb $end
$var wire 32 ! pc [31:0] $end
$var reg 1 " clk $end
$var reg 32 # next_pc [31:0] $end
$var reg 1 $ reset $end
$scope module uut $end
$var wire 1 " clk $end
$var wire 32 % next_pc [31:0] $end
$var wire 1 $ reset $end
$var reg 32 & pc [31:0] $end
$upscope $end
$upscope $end
$enddefinitions $end
$comment Show the parameter values. $end
$dumpall
$end
#0
$dumpvars
b0 &
b0 %
1$
b0 #
0"
b0 !
$end
#5000
1"
#10000
0"
b100 #
b100 %
0$
#15000
b100 !
b100 &
1"
#20000
0"
b1000 #
b1000 %
#25000
b1000 !
b1000 &
1"
#30000
0"
b1100 #
b1100 %
#35000
b1100 !
b1100 &
1"
#40000
0"
b10000 #
b10000 %
#45000
b10000 !
b10000 &
1"
